json_log_display/__init__.py
json_log_display/__main__.py
json_log_display/cli.py
json_log_display/pkg_meta.py
json_log_display-0.0.1.dist-info/LICENSE
json_log_display-0.0.1.dist-info/METADATA
json_log_display-0.0.1.dist-info/WHEEL
json_log_display-0.0.1.dist-info/entry_points.txt
json_log_display-0.0.1.dist-info/top_level.txt
json_log_display-0.0.1.dist-info/RECORD
