Metadata-Version: 2.1
Name: json-log-display
Version: 0.0.1
Summary: Strict Text Template Parsing
Home-page: https://github.com/mwri/json-log-display
Author: Michael Wright
Author-email: mjw@methodanalysis.com
License: UNKNOWN
Platform: UNKNOWN
Classifier: Programming Language :: Python :: 3
Classifier: License :: OSI Approved :: MIT License
Classifier: Operating System :: OS Independent
Requires-Python: >=3.6
Requires-Dist: ansicolors (>=1.1.8)
Provides-Extra: dev
Requires-Dist: Sphinx (==4.4.0) ; extra == 'dev'
Requires-Dist: black (==22.10.0) ; extra == 'dev'
Requires-Dist: isort (==5.10.1) ; extra == 'dev'
Requires-Dist: sphinx-rtd-theme (==1.0.0) ; extra == 'dev'
